line_progressor.py
line_progressor-0.1.2.dist-info/licenses/LICENSE
line_progressor-0.1.2.dist-info/METADATA
line_progressor-0.1.2.dist-info/WHEEL
line_progressor-0.1.2.dist-info/entry_points.txt
line_progressor-0.1.2.dist-info/top_level.txt
line_progressor-0.1.2.dist-info/RECORD
