Metadata-Version: 2.4
Name: line-progressor
Version: 0.1.2
Summary: Colored one-line progress bar with stdout interception
Author: František Dvořák
License-Expression: MIT
Project-URL: Homepage, https://gitlab.com/<user>/<repo>
Project-URL: Issues, https://gitlab.com/<user>/<repo>/-/issues
Keywords: progress,cli,terminal,ansi
Classifier: Programming Language :: Python :: 3
Classifier: Environment :: Console
Classifier: Topic :: Utilities
Requires-Python: >=3.8
License-File: LICENSE
Requires-Dist: colorama>=0.4
Dynamic: license-file
